LICENSE
MANIFEST.in
README.rst
setup.py
Argot.egg-info/PKG-INFO
Argot.egg-info/SOURCES.txt
Argot.egg-info/dependency_links.txt
Argot.egg-info/not-zip-safe
Argot.egg-info/requires.txt
Argot.egg-info/top_level.txt
argot/__init__.py
argot/markup.py
argot/utils.py
bin/argot