Metadata-Version: 1.0
Name: Argot
Version: 0.5.3
Summary: argot text markup -- a markdown dialect
Home-page: http://dev.jmoiron.net/hg/argot/
Author: Jason Moiron
Author-email: jmoiron@jmoiron.net
License: MIT
Keywords: html markup markdown
Platform: UNKNOWN
Classifier: Development Status :: 3 - Alpha
Classifier: Intended Audience :: Developers
Classifier: License :: OSI Approved :: MIT License
Classifier: Programming Language :: Python
Classifier: Operating System :: OS Independent
Classifier: Topic :: Internet :: WWW/HTTP :: Dynamic Content :: CGI Tools/Libraries
Classifier: Topic :: Text Processing :: Markup :: HTML
